abstrys/__init__.py
abstrys/cmd_rst2db.py
abstrys/docutils_ext/__init__.py
abstrys/docutils_ext/docbook_writer.py
abstrys/sphinx_ext/__init__.py
abstrys/sphinx_ext/docbook_builder.py
msrst2db-1.4.dist-info/DESCRIPTION.rst
msrst2db-1.4.dist-info/METADATA
msrst2db-1.4.dist-info/RECORD
msrst2db-1.4.dist-info/WHEEL
msrst2db-1.4.dist-info/entry_points.txt
msrst2db-1.4.dist-info/metadata.json
msrst2db-1.4.dist-info/top_level.txt
