Metadata-Version: 2.0
Name: msrst2db
Version: 1.4
Summary:         A reStructuredText to DocBook converter using Python's docutils.
Home-page: https://github.com/Aleksei-Badyaev/rst2db
Author: Aleksei Badyaev
Author-email: a.badyaev@mousesoft.tk
License: UNKNOWN
Platform: UNKNOWN
Requires-Dist: docutils (>=0.12)
Requires-Dist: lxml (>=2.3)
Provides-Extra: dev
Requires-Dist: check-manifest; extra == 'dev'
Requires-Dist: ipdb; extra == 'dev'
Requires-Dist: twine; extra == 'dev'
Requires-Dist: wheel; extra == 'dev'
